{
    "CiudadOrigen":{
        "0":"Madrid",
        "1":"Madrid",
        "2":"Barcelona",
        "3":"Sevilla",
        "4":"Valencia",
        "5":"Madrid"
    },
    "CiudadDestino":{
        "0":"Barcelona",
        "1":"Valencia",
        "2":"Madrid",
        "3":"Madrid",
        "4":"Barcelona",
        "5":"Sevilla"
    },
    "Fecha":{
        "0":"2024-01-05",
        "1":"2024-01-07",
        "2":"2024-01-08",
        "3":"2024-01-10",
        "4":"2024-01-12",
        "5":"2024-01-14"
    },
    "Medio":{
        "0":"Tren",
        "1":"Bus",
        "2":"Avi\u00f3n",
        "3":"Avi\u00f3n",
        "4":"Tren",
        "5":"Tren"
    },
    "Distancia_km":{
        "0":620,
        "1":360,
        "2":620,
        "3":530,
        "4":350,
        "5":530
    },
    "Precio":{
        "0":55,
        "1":28,
        "2":95,
        "3":80,
        "4":45,
        "5":52
    }
}